json_flatten.py
json_flatten-0.3.1.dist-info/LICENSE
json_flatten-0.3.1.dist-info/METADATA
json_flatten-0.3.1.dist-info/WHEEL
json_flatten-0.3.1.dist-info/top_level.txt
json_flatten-0.3.1.dist-info/RECORD
