Metadata-Version: 2.1
Name: json-flatten
Version: 0.3.1
Summary: Python functions for flattening a JSON object to a single dictionary of pairs, and unflattening that dictionary back to a JSON object
Home-page: https://github.com/simonw/json-flatten
Author: Simon Willison
License: Apache License, Version 2.0
Project-URL: Issues, https://github.com/simonw/json-flatten/issues
Project-URL: CI, https://github.com/simonw/json-flatten/actions
Project-URL: Changelog, https://github.com/simonw/json-flatten/releases
License-File: LICENSE
Provides-Extra: test
Requires-Dist: pytest ; extra == 'test'
Requires-Dist: black ; extra == 'test'
Requires-Dist: cogapp ; extra == 'test'
